Workbook

Sheet 01_Parametros_Supuestos
B2: MODELO DE VALORACIÓN FINANCIERA — SISTEMA AUTÓNOMO DE MONITOREO
B3: Universidad Nacional de Ingeniería (FIIS UNI) | Proyecto de Inversión Tecnológica
B5: Parámetro Macroeconómico / Operativo | C5: Valor | D5: Unidad / Formato | E5: Descripción Técnica y Justificación
B6: INVERSIÓN INICIAL & ACTIVOS
B7: Inversión Inicial en Activo Fijo (CAPEX) | C7: 250000 | D7: $#,##0 | E7: Equipamiento de drones, sensores IoT, servidores edge
B8: Vida Útil del Proyecto (Años) | C8: 5 | D8: 0 | E8: Horizonte de evaluación económica
B9: Depreciación Anual Lineal | C9: =B6/B7 | D9: $#,##0 | E9: Método de línea recta sin valor de desecho contable
B10: Valor Residual de Mercado (Fin de Año 5) | C10: 35000 | D10: $#,##0 | E10: Valor de recuperación de equipos
B12: OPERACIÓN COMERCIAL & DEMANDA
B13: Volumen de Servicio Base - Año 1 (Horas/Unid) | C13: 12000 | D13: #,##0 | E13: Capacidad comercial proyectada
B14: Precio Unitario Base ($/Hora de Inspección) | C14: 55 | D14: $#,##0.00 | E14: Tarifa por hora de servicio de telemetría
B15: Costo Variable Unitario ($/Hora) | C15: 22 | D15: $#,##0.00 | E15: Baterías, consumibles, mantenimiento directo
B16: Costos Fijos Operativos Anuales (OPEX) | C16: 95000 | D16: $#,##0 | E16: Personal especializado, seguros, nube, soporte
B17: Tasa de Crecimiento Anual del Volumen | C17: 0.08 | D17: 0.0% | E17: Penetración de mercado proyectada
B18: Tasa de Inflación Anual de Precios | C18: 0.03 | D18: 0.0% | E18: Ajuste tarifario anual
B19: Tasa de Inflación Anual de Costos | C19: 0.025 | D19: 0.0% | E19: Incremento salarial y de insumos
B21: FINANZAS CORPORATIVAS & IMPUESTOS
B22: Tasa de Impuesto a la Renta (Perú) | C22: 0.295 | D22: 0.0% | E22: Régimen General de Impuesto a la Renta (SUNAT)
B23: Costo Promedio Ponderado de Capital (WACC) | C23: 0.115 | D23: 0.0% | E23: Tasa de descuento de los flujos libres de caja (FCFF)

Sheet 02_Flujo_Caja_DCF
B2: ESTADO DE RESULTADOS PRO-FORMA & FLUJO DE CAJA LIBRE DESCONTADO (DCF)
B4: Rubro Financiero / Año | C4: Año 0 | D4: Año 1 | E4: Año 2 | F4: Año 3 | G4: Año 4 | H4: Año 5
B5: 1. Volumen de Servicios (Horas) | C5: - | D5: ='01_Parametros_Supuestos'!$C$11 | E5: =D5*(1+'01_Parametros_Supuestos'!$C$15) | F5: =E5*(1+'01_Parametros_Supuestos'!$C$15) | G5: =F5*(1+'01_Parametros_Supuestos'!$C$15) | H5: =G5*(1+'01_Parametros_Supuestos'!$C$15)
B6: 2. Precio Unitario Promedio ($) | C6: - | D6: ='01_Parametros_Supuestos'!$C$12 | E6: =D6*(1+'01_Parametros_Supuestos'!$C$16) | F6: =E6*(1+'01_Parametros_Supuestos'!$C$16) | G6: =F6*(1+'01_Parametros_Supuestos'!$C$16) | H6: =G6*(1+'01_Parametros_Supuestos'!$C$16)
B7: 3. Costo Variable Unitario ($) | C7: - | D7: ='01_Parametros_Supuestos'!$C$13 | E7: =D7*(1+'01_Parametros_Supuestos'!$C$17) | F7: =E7*(1+'01_Parametros_Supuestos'!$C$17) | G7: =F7*(1+'01_Parametros_Supuestos'!$C$17) | H7: =G7*(1+'01_Parametros_Supuestos'!$C$17)
B8: (=) Ingresos Operativos Brutos | C8: - | D8: =D5*D6 | E8: =E5*E6 | F8: =F5*F6 | G8: =G5*G6 | H8: =H5*H6
B9: (-) Costos Variables Totales | C9: - | D9: =D5*D7 | E9: =E5*E7 | F9: =F5*F7 | G9: =G5*G7 | H9: =H5*H7
B10: (=) Margen de Contribución | C10: - | D10: =D8-D9 | E10: =E8-E9 | F10: =F8-F9 | G10: =G8-G9 | H10: =H8-H9
B11: (-) Costos Fijos Operativos (OPEX) | C11: - | D11: ='01_Parametros_Supuestos'!$C$14 | E11: =E11*(1+'01_Parametros_Supuestos'!$C$17) | F11: =F11*(1+'01_Parametros_Supuestos'!$C$17) | G11: =G11*(1+'01_Parametros_Supuestos'!$C$17) | H11: =H11*(1+'01_Parametros_Supuestos'!$C$17)
B12: (-) Depreciación de Activos | C12: - | D12: ='01_Parametros_Supuestos'!$C$8 | E12: ='01_Parametros_Supuestos'!$C$8 | F12: ='01_Parametros_Supuestos'!$C$8 | G12: ='01_Parametros_Supuestos'!$C$8 | H12: ='01_Parametros_Supuestos'!$C$8
B13: (=) Utilidad Antes de Intereses e Impuestos (EBIT) | C13: - | D13: =D10-D11-D12 | E13: =E10-E11-E12 | F13: =F10-F11-F12 | G13: =G10-G11-G12 | H13: =H10-H11-H12
B14: (-) Impuesto a la Renta (29.5%) | C14: - | D14: =D13*'01_Parametros_Supuestos'!$C$19 | E14: =E13*'01_Parametros_Supuestos'!$C$19 | F14: =F13*'01_Parametros_Supuestos'!$C$19 | G14: =G13*'01_Parametros_Supuestos'!$C$19 | H14: =H13*'01_Parametros_Supuestos'!$C$19
B15: (=) Utilidad Operativa Neta Después de Impuestos (NOPAT) | C15: - | D15: =D13-D14 | E15: =E13-E14 | F15: =F13-F14 | G15: =G13-G14 | H15: =H13-H14
B16: (+) Ajuste por Depreciación (No salida de caja) | C16: - | D16: =D12 | E16: =E12 | F16: =F12 | G16: =G12 | H16: =H12
B17: (-) Inversión Inicial en Activos (CAPEX) | C17: =-'01_Parametros_Supuestos'!$C$6 | D17: 0 | E17: 0 | F17: 0 | G17: 0 | H17: 0
B18: (+) Valor de Rescate de Activos | C18: 0 | D18: 0 | E18: 0 | F18: 0 | G18: 0 | H18: ='01_Parametros_Supuestos'!$C$9
B19: (=) FLUJO DE CAJA LIBRE DEL PROYECTO (FCFF) | C19: =C17 | D19: =D15+D16+D17+D18 | E19: =E15+E16+E17+E18 | F19: =F15+F16+F17+F18 | G19: =G15+G16+G17+G18 | H19: =H15+H16+H17+H18
B20: Factor de Descuento WACC (t) | C20: 1 | D20: =1/(1+'01_Parametros_Supuestos'!$C$20)^1 | E20: =1/(1+'01_Parametros_Supuestos'!$C$20)^2 | F20: =1/(1+'01_Parametros_Supuestos'!$C$20)^3 | G20: =1/(1+'01_Parametros_Supuestos'!$C$20)^4 | H20: =1/(1+'01_Parametros_Supuestos'!$C$20)^5
B21: Flujo de Caja Descontado (Valor Presente) | C21: =C19*C20 | D21: =D19*D20 | E21: =E19*E20 | F21: =F19*F20 | G21: =G19*G20 | H21: =H19*H20
B22: Flujo de Caja Descontado Acumulado | C22: =C21 | D22: =C22+D21 | E22: =D22+E21 | F22: =E22+F21 | G22: =F22+G21 | H22: =G22+H21
B25: INDICADORES CLAVE DE DECISIÓN FINANCIERA (KPIs)
B26: Valor Actual Neto (VAN / NPV) | C26: =NPV('01_Parametros_Supuestos'!$C$20, D19:H19)+C19 | D26: VAN > 0 indica creación neta de valor
B27: Tasa Interna de Retorno (TIR / IRR) | C27: =IRR(C19:H19) | D27: Rentabilidad intrínseca del flujo de fondos
B28: WACC / Tasa de Descuento de Referencia | C28: ='01_Parametros_Supuestos'!$C$20 | D28: Costo promedio ponderado de capital
B29: Spread de Rentabilidad (TIR - WACC) | C29: =C27-C28 | D29: Margen de seguridad financiero sobre costo de capital
B30: Índice de Rentabilidad (B/C Ratio) | C30: =SUM(D21:H21)/ABS(C19) | D30: Dólares recuperados por cada dólar invertido
B31: Decisión Económica Recomendada | C31: =IF(C26>0, "APROBAR PROYECTO (CREA VALOR)", "RECHAZAR") | D31: Criterio normativo de finanzas corporativas

Sheet 03_Sensibilidad_Bidimensional
B2: ANÁLISIS DE SENSIBILIDAD BIDIMENSIONAL DEL VAN ($)
B3: Impacto cruzado: Variaciones de Tasa de Descuento (WACC) vs Precio Unitario de Venta
B5: WACC \ Precio | C5: $45.00 | D5: $50.00 | E5: $55.00 | F5: $60.00 | G5: $65.00
B6: 9.5% | C6: 485518.61 | D6: 684906.1 | E6: 884293.59 | F6: 1083681.1 | G6: 1283068.6
B7: 10.5% | C7: 464841.1 | D7: 658824.63 | E7: 852808.15 | F7: 1046791.7 | G7: 1240775.2
B8: 11.5% | C8: 445039.09 | D8: 633842.61 | E8: 822646.14 | F8: 1011449.7 | G8: 1200253.2
B9: 12.5% | C9: 426065.79 | D9: 609901.49 | E9: 793737.2 | F9: 977572.9 | G9: 1161408.6
B10: 13.5% | C10: 407877.42 | D10: 586946.42 | E10: 766015.42 | F10: 945084.42 | G10: 1124153.4

Sheet 04_Simulacion_MonteCarlo
B2: SIMULACIÓN ESTOCÁSTICA DE MONTE CARLO (N = 5,000 ESCENARIOS)
B3: Evaluación de Riesgo Cuantitativo y Distribución de Probabilidad del VAN
B5: MÉTRICAS ESTADÍSTICAS DEL VAN SIMULADO | C5: VALOR | D5: DESCRIPCIÓN TÉCNICA
B6: Media Esperada del VAN (E[VAN]) | C6: 809323.57 | D6: Valor central esperado de la distribución estocástica
B7: Mediana del VAN | C7: 801276.05 | D7: Percentil 50 libre de sesgo por asimetría
B8: Desviación Estándar (Volatilidad del VAN) | C8: 206180.47 | D8: Dispersión de riesgo alrededor de la media
B9: Value at Risk (VaR 95% Cuantitativo) | C9: 480227.47 | D9: En el 95% de los escenarios el VAN superará este umbral
B10: Conditional VaR / Expected Shortfall (CVaR 95%) | C10: 408683.3 | D10: Pérdida esperada en el 5% de los peores escenarios extremos
B11: Percentil 95 (Escenario Optimista) | C11: 1165595.5 | D11: Cota superior en condiciones macroeconómicas favorables
B12: Probabilidad de Éxito P(VAN > 0) | C12: 1 | D12: Porcentaje de simulaciones donde el proyecto genera valor económico
B13: Probabilidad de Riesgo de Pérdida P(VAN <= 0) | C13: 0 | D13: Probabilidad acumulada de destrucción de capital
B16: Iteración | C16: Demanda (Horas) | D16: Precio ($) | E16: Costo Var ($) | F16: WACC (%) | G16: VAN Simulado ($)
B17: 1 | C17: 12695.4 | D17: 53.52 | E17: 21.6 | F17: 0.1478 | G17: 759009.54
B18: 2 | C18: 11806.4 | D18: 53.41 | E18: 20.47 | F18: 0.1218 | G18: 780277.05
B19: 3 | C19: 12906.8 | D19: 48.72 | E19: 20.23 | F19: 0.1074 | G19: 754274.94
B20: 4 | C20: 14132.2 | D20: 53.84 | E20: 20.41 | F20: 0.1192 | G20: 1049356.8
B21: 5 | C21: 11672.2 | D21: 57.56 | E21: 22.58 | F21: 0.1364 | G21: 798944.25
B22: 6 | C22: 11672.2 | D22: 50.54 | E22: 20.04 | F22: 0.137 | G22: 641071.19
B23: 7 | C23: 14210.9 | D23: 58.67 | E23: 21.66 | F23: 0.1081 | G23: 1261278.3
B24: 8 | C24: 13074.4 | D24: 56.71 | E24: 23.37 | F24: 0.118 | G24: 939355.08
B25: 9 | C25: 11342.7 | D25: 52.43 | E25: 21.49 | F25: 0.0978 | G25: 726126.07
B26: 10 | C26: 12759.6 | D26: 54.5 | E26: 23.43 | F26: 0.1249 | G26: 796755.39
B27: 11 | C27: 11351.2 | D27: 60.59 | E27: 23.33 | F27: 0.1336 | G27: 850575.32
B28: 12 | C28: 11348 | D28: 57.57 | E28: 21.27 | F28: 0.1155 | G28: 870454.73
... B5016: 5000 | C5016: 10812.7 | D5016: 57.26 | E5016: 22.37 | F5016: 0.1146 | G5016: 764111.26

Sheet 05_PowerQuery_M_Script
B2: FLUJO DE EXTRACCIÓN & TRANSFORMACIÓN ETL CON POWER QUERY (M CODE)
B3: Automatización del Pipeline de Ingesta desde Base Operacional SQL / ERP
B5: Script de Consulta Power Query (Lenguaje M):
B7: // Código M (Power Query) para consolidar horas de vuelo y telemetría de drones let // 1. Origen: Conexión a Base de Datos Operacional de Telemetría SQLite Origen = Sqlite.Database("C:\Users\USUARIO\Desktop\CV\portafolio\09-python-telemetry-streaming\output\benchmark_telemetry.db"), telemetry_events = Origen{[Schema="",Item="telemetry_events"]}[Data], // 2. Filtrar únicamente eventos exitosos sin anomalías críticas FiltrarValidos = Table.SelectRows(telemetry_events, each ([is_anomalous] = 0)), // 3. Parsear fecha y timestamp TipoCambiado = Table.TransformColumnTypes(FiltrarValidos, { {"event_timestamp", type datetimezone}, {"device_id", type text}, {"latency_ms", type number} }), // 4. Agregar columna de periodo contable (Año-Mes) AgregarPeriodo = Table.AddColumn(TipoCambiado, "Periodo", each DateTimeZone.ToText([event_timestamp], "yyyy-MM"), type text), // 5. Agrupación mensual para cálculo de Horas Operativas de Vuelo Agrupado = Table.Group(AgregarPeriodo, {"Periodo", "device_id"}, { {"Total_Eventos_Sensor", each Table.RowCount(_), Int64.Type}, {"Latencia_Promedio_ms", each List.Average([latency_ms]), type number} }), // 6. Cálculo de Horas Equivalentes de Inspección para Facturación DCF HorasEquivalentes = Table.AddColumn(Agrupado, "Horas_Facturables", each [Total_Eventos_Sensor] / 3600, type number) in HorasEquivalentes
